{"version":1,"resource":"vscode-remote://wsl%2Bubuntu/home/coder123/personal_site/style.css","entries":[{"id":"Uwxg.css","timestamp":1720844978248},{"id":"1ZJL.css","timestamp":1720845426468},{"id":"UnS5.css","source":"undoRedo.source","timestamp":1720845717268},{"id":"fwPE.css","timestamp":1720846213438},{"id":"EGWi.css","timestamp":1720846459508},{"id":"TIBq.css","timestamp":1720923499156},{"id":"eBDw.css","timestamp":1720926509090},{"id":"eHvR.css","timestamp":1721106485592},{"id":"JKTu.css","timestamp":1721108160872},{"id":"V8p9.css","timestamp":1721108180262},{"id":"kUzg.css","timestamp":1721108199962},{"id":"8jQu.css","timestamp":1721108252252},{"id":"ZQC4.css","timestamp":1721108378331},{"id":"4SCQ.css","timestamp":1721108716711}]}